.dockerignore
Dockerfile
LICENSE
MANIFEST.in
README.md
VERSION
check_license.py
check_sage_testsuite.py
check_testsuite.py
docker-setup.sh
environment.yml
pyproject.toml
requirements.txt
setup.py
tox.ini
sage_numerical_backends_gurobi/__init__.py
sage_numerical_backends_gurobi/gurobi_backend.pxd
sage_numerical_backends_gurobi/gurobi_backend.pyx
sage_numerical_backends_gurobi.egg-info/PKG-INFO
sage_numerical_backends_gurobi.egg-info/SOURCES.txt
sage_numerical_backends_gurobi.egg-info/dependency_links.txt
sage_numerical_backends_gurobi.egg-info/requires.txt
sage_numerical_backends_gurobi.egg-info/top_level.txt